custom_math_lib/__init__.py
custom_math_lib/ai_math.py
custom_math_lib/crypto.py
custom_math_lib/matrix.py
custom_math_lib-0.1.dist-info/LICENSE
custom_math_lib-0.1.dist-info/METADATA
custom_math_lib-0.1.dist-info/WHEEL
custom_math_lib-0.1.dist-info/top_level.txt
custom_math_lib-0.1.dist-info/RECORD
